pyreelmaker/__init__.py
pyreelmaker/merger.py
pyreelmaker/segmenter.py
pyreelmaker/utils.py
pyreelmaker-1.0.0.dist-info/LICENSE
pyreelmaker-1.0.0.dist-info/METADATA
pyreelmaker-1.0.0.dist-info/WHEEL
pyreelmaker-1.0.0.dist-info/top_level.txt
pyreelmaker-1.0.0.dist-info/RECORD
