Metadata-Version: 2.1
Name: pyreelmaker
Version: 1.0.0
Summary: A Python package for creating short video reels.
Home-page: UNKNOWN
Author: Jaswanth Krishna Perla
Author-email: perlajaswanthkrishna@gmail.com
License: UNKNOWN
Platform: UNKNOWN
Requires-Python: >=3.7
Requires-Dist: moviepy
Requires-Dist: ffmpeg-python
